jira_validator/agent.py
jira_validator/exceptions.py
jira_validator/init.py
jira_validator-0.1.0.dist-info/licenses/LICENSE
jira_validator-0.1.0.dist-info/METADATA
jira_validator-0.1.0.dist-info/WHEEL
jira_validator-0.1.0.dist-info/top_level.txt
jira_validator-0.1.0.dist-info/RECORD
