Metadata-Version: 2.4
Name: jira-validator
Version: 0.1.0
Summary: A library to validate Jira user stories for structure and quality.
Author-email: Aayush Jha <2000149350@hexaware.com>
License: MIT
Classifier: Programming Language :: Python :: 3
Classifier: License :: OSI Approved :: MIT License
Classifier: Operating System :: OS Independent
Requires-Python: >=3.8
License-File: LICENSE
Requires-Dist: google-adk
Requires-Dist: nest-asyncio
Requires-Dist: python-dotenv
Requires-Dist: boto3
Requires-Dist: neo4j
Requires-Dist: litellm
Requires-Dist: langchain-openai
Requires-Dist: langchain-community
Requires-Dist: grpcio-status>=1.62.0
Requires-Dist: opentelemetry-proto>=1.25.0
Requires-Dist: fastapi
Requires-Dist: uvicorn
Requires-Dist: psycopg2-binary
Requires-Dist: arize-phoenix
Requires-Dist: phoenix
Requires-Dist: openinference-instrumentation-google-adk
Requires-Dist: arize-phoenix-otel
Dynamic: license-file
